odoo10_addon_account_tax_unece-10.0.1.1.1-py2.7-nspkg.pth
odoo/addons/account_tax_unece/README.rst
odoo/addons/account_tax_unece/__init__.py
odoo/addons/account_tax_unece/__manifest__.py
odoo/addons/account_tax_unece/data/unece_date.xml
odoo/addons/account_tax_unece/data/unece_tax_categ.xml
odoo/addons/account_tax_unece/data/unece_tax_type.xml
odoo/addons/account_tax_unece/models/__init__.py
odoo/addons/account_tax_unece/models/account_tax.py
odoo/addons/account_tax_unece/models/account_tax_template.py
odoo/addons/account_tax_unece/models/unece_code_list.py
odoo/addons/account_tax_unece/views/account_tax.xml
odoo/addons/account_tax_unece/views/account_tax_template.xml
odoo10_addon_account_tax_unece-10.0.1.1.1.dist-info/DESCRIPTION.rst
odoo10_addon_account_tax_unece-10.0.1.1.1.dist-info/METADATA
odoo10_addon_account_tax_unece-10.0.1.1.1.dist-info/RECORD
odoo10_addon_account_tax_unece-10.0.1.1.1.dist-info/WHEEL
odoo10_addon_account_tax_unece-10.0.1.1.1.dist-info/metadata.json
odoo10_addon_account_tax_unece-10.0.1.1.1.dist-info/namespace_packages.txt
odoo10_addon_account_tax_unece-10.0.1.1.1.dist-info/top_level.txt
